{
    "buy_now": "Beli sekarang",
    "you_need_to_buy_vip": "Anda perlu membeli lisensi VIP untuk menerima komisi VIP dan komisi perdagangan",
    "registration_link": "Tautan pendaftaran",
    "invitation_code": "Kode undangan",
    "copy": "Salinan",
    "invite_friend": "Mengundang teman-teman",
    "invite_friend_to_register": "Undang teman untuk mendaftar TdTrade.us melalui tautan",
    "friend_signup": "Pendaftaran teman",
    "friend_accept_the_invitation": "Teman menerima undangan, menyelesaikan pendaftaran dan bermain",
    "get_a_corresponding": "Dapatkan proporsi komisi yang sesuai",
    "easily_get_commission": "Dapatkan komisi dengan mudah",
    "confirm_your_participation": "Konfirmasi Partisipasi Anda",
    "pay_to_become_VIP": "Bayar ${{price}} untuk menjadi anggota VIP. Apakah Anda ingin membayar?",
    "i_confirm_accept": "Saya mengkonfirmasi dan menerima",
    "i_have_read_accept": "Saya telah membaca dan menerima",
    "terms_of_service": "Persyaratan Layanan",
    "vip_obligations": "Kewajiban VIP",
    "your_balance_not_enough": "Saldo Anda Tidak Cukup",
    "confirm": "Mengonfirmasi",
    "overview": "Ringkasan",
    "commission": "Komisi",
    "system": "Sistem",
    "vip_member": "Anggota VIP",
    "all_member": "Semua anggota",
    "level_condition": "Kondisi Tingkat",
    "f1_total": "Total F1 (minggu ini)",
    "f1_vip_member": "Anggota vip F1",
    "presenter": "Pembawa acara",
    "total_number_of_trade": "Jumlah total pedagang",
    "total_vip_member": "Jumlah anggota VIP",
    "trading_commissions": "Komisi perdagangan",
    "commission_vip_member": "Anggota Komisi VIP",
    "this_month": "Bulan ini",
    "last_month": "Bulan lalu",
    "recent_figures": "Angka terbaru",
    "total_number_of_new_traders": "Jumlah total pedagang baru",
    "total_new_vip_members": "Jumlah Anggota VIP Baru",
    "total_new_commission": "Total komisi baru",
    "trading_volume_of_subordinates": "Volume perdagangan bawahan",
    "trading_commission": "Komisi perdagangan",
    "commission_type": "Jenis komisi",
    "trading_commission_chart": "Bagan Komisi Perdagangan",
    "trading_profit_details": "Detail Laba Perdagangan",
    "commission_vip_details": "Detail Komisi VIP",
    "duration": "Durasi",
    "payment": "Pembayaran",
    "number_of_traders": "Jumlah Pedagang",
    "number_of_transactions": "Jumlah Transaksi",
    "trading_volume": "Volume perdagangan",
    "every_new_day_you_get_commission": "Setiap hari baru Anda akan mendapatkan komisi trading dari downline hari sebelumnya",
    "member": "Anggota",
    "rank": "Pangkat",
    "date": "Tanggal",
    "vip_member_management": "Manajemen Anggota VIP",
    "search_by": "Cari berdasarkan",
    "search": "Mencari",
    "see_friend_by_rank": "Lihat Teman yang Direferensikan berdasarkan Peringkat",
    "see_friend_by_nick_name": "Lihat Teman yang Direferensikan berdasarkan nama panggilan",
    "nickname": "Nama panggilan",
    "level": "Tingkat",
    "total_trading_volume": "Total volume perdagangan",
    "commission_received": "Komisi diterima"
}